Constellation_Vote-0.1.2.dist-info/DESCRIPTION.rst
Constellation_Vote-0.1.2.dist-info/METADATA
Constellation_Vote-0.1.2.dist-info/RECORD
Constellation_Vote-0.1.2.dist-info/WHEEL
Constellation_Vote-0.1.2.dist-info/metadata.json
Constellation_Vote-0.1.2.dist-info/top_level.txt
constellation_vote/__init__.py
constellation_vote/models.py
constellation_vote/urls.py
constellation_vote/utils.py
constellation_vote/views.py
constellation_vote/migrations/0001_initial.py
constellation_vote/migrations/0002_pollstart.py
constellation_vote/migrations/__init__.py
constellation_vote/static/constellation_vote/css/getmdl-select.min.css
constellation_vote/static/constellation_vote/css/vote.css
constellation_vote/static/constellation_vote/js/ballot.js
constellation_vote/static/constellation_vote/js/getmdl-select.min.js
constellation_vote/static/constellation_vote/js/manage-poll.js
constellation_vote/templates/constellation_vote/ballot.html
constellation_vote/templates/constellation_vote/ballotItem.html
constellation_vote/templates/constellation_vote/dashboard.html
constellation_vote/templates/constellation_vote/error.html
constellation_vote/templates/constellation_vote/list.html
constellation_vote/templates/constellation_vote/manage-poll.html
constellation_vote/templates/constellation_vote/view_results.html
constellation_vote/templatetags/__init__.py
constellation_vote/templatetags/get_item.py
